airbyte_ops_mcp/__init__.py
airbyte_ops_mcp/_sentry.py
airbyte_ops_mcp/constants.py
airbyte_ops_mcp/docker_hub.py
airbyte_ops_mcp/gcp_auth.py
airbyte_ops_mcp/github_actions.py
airbyte_ops_mcp/github_api.py
airbyte_ops_mcp/metadata_validator.py
airbyte_ops_mcp/py.typed
airbyte_ops_mcp/telemetry.py
airbyte_ops_mcp/_legacy/__init__.py
airbyte_ops_mcp/_legacy/airbyte_ci/README.md
airbyte_ops_mcp/_legacy/airbyte_ci/connector_erd_generator/README.md
airbyte_ops_mcp/_legacy/airbyte_ci/connector_erd_generator/__init__.py
airbyte_ops_mcp/_legacy/airbyte_ci/connector_erd_generator/dbml_assembler.py
airbyte_ops_mcp/_legacy/airbyte_ci/connector_erd_generator/erd_service.py
airbyte_ops_mcp/_legacy/airbyte_ci/connector_erd_generator/relationships.py
airbyte_ops_mcp/_legacy/airbyte_ci/connector_insights/README.md
airbyte_ops_mcp/_legacy/airbyte_ci/connector_insights/__init__.py
airbyte_ops_mcp/_legacy/airbyte_ci/connector_insights/cli.py
airbyte_ops_mcp/_legacy/airbyte_ci/connector_insights/hacks.py
airbyte_ops_mcp/_legacy/airbyte_ci/connector_insights/insights.py
airbyte_ops_mcp/_legacy/airbyte_ci/connector_insights/models.py
airbyte_ops_mcp/_legacy/airbyte_ci/connector_insights/pylint.py
airbyte_ops_mcp/_legacy/airbyte_ci/connector_insights/result_backends.py
airbyte_ops_mcp/_legacy/airbyte_ci/connector_insights/utils.py
airbyte_ops_mcp/_legacy/airbyte_ci/connector_insights/pylint_plugins/cdk_deprecation_checkers.py
airbyte_ops_mcp/_legacy/airbyte_ci/connector_ops/README.md
airbyte_ops_mcp/_legacy/airbyte_ci/connector_ops/__init__.py
airbyte_ops_mcp/_legacy/airbyte_ci/connector_ops/utils.py
airbyte_ops_mcp/_legacy/airbyte_ci/connector_pipelines/README.md
airbyte_ops_mcp/_legacy/airbyte_ci/connector_pipelines/__init__.py
airbyte_ops_mcp/_legacy/airbyte_ci/connector_pipelines/consts.py
airbyte_ops_mcp/_legacy/airbyte_ci/connector_pipelines/hacks.py
airbyte_ops_mcp/_legacy/airbyte_ci/connector_pipelines/DELETEME-dagger/README.md
airbyte_internal_ops-0.9.1.dist-info/METADATA
airbyte_internal_ops-0.9.1.dist-info/WHEEL
airbyte_internal_ops-0.9.1.dist-info/entry_points.txt
airbyte_internal_ops-0.9.1.dist-info/RECORD
