Metadata-Version: 2.4
Name: airbyte-internal-ops
Version: 0.9.1
Summary: MCP and API interfaces that let the agents do the admin work
Author-email: Aaron Steers <aj@airbyte.io>
Keywords: admin,airbyte,api,mcp
Classifier: Development Status :: 4 - Beta
Classifier: Intended Audience :: Developers
Classifier: License :: OSI Approved :: MIT License
Classifier: Programming Language :: Python :: 3
Classifier: Programming Language :: Python :: 3.11
Classifier: Programming Language :: Python :: 3.12
Requires-Python: <3.13,>=3.11
Requires-Dist: airbyte-cdk<8.0,>=7.3.9
Requires-Dist: airbyte-connector-models<=0.1.4,>=0.1.3
Requires-Dist: airbyte-protocol-models-pdv2>=0.13.0
Requires-Dist: airbyte==0.35.4
Requires-Dist: asyncclick<9.0,>=8.1.7
Requires-Dist: asyncer<1.0,>=0.0.4
Requires-Dist: click<9.0,>=8.1.3
Requires-Dist: cloud-sql-python-connector[pg8000]<2.0,>=1.7.0
Requires-Dist: cyclopts<5.0,>=4.0.0
Requires-Dist: docker<7.0,>=6.0
Requires-Dist: dpath<3.0,>=2.1.5
Requires-Dist: fastmcp-extensions<1.0,>=0.2.0
Requires-Dist: fastmcp<3.0,>=2.12.1
Requires-Dist: gitpython<4.0,>=3.1.29
Requires-Dist: google-cloud-logging<4.0,>=3.9.0
Requires-Dist: google-cloud-secret-manager<3.0,>=2.18.0
Requires-Dist: google-cloud-storage<3.0,>=2.8.0
Requires-Dist: jinja2<4.0,>=3.1.2
Requires-Dist: markdown-it-py<3.0,>=2.2.0
Requires-Dist: pydantic>=2.0.0
Requires-Dist: pydash<8.0,>=6.0.2
Requires-Dist: pygithub<3.0,>=2.0
Requires-Dist: python-dotenv<2.0,>=1.0.0
Requires-Dist: pyyaml<7.0,>=6.0.0
Requires-Dist: requests<3.0,>=2.31.0
Requires-Dist: rich<14.0,>=13.0.0
Requires-Dist: semver<4.0,>=3.0.1
Requires-Dist: sentry-sdk>=2.50.0
Requires-Dist: simpleeval<1.0,>=0.9.13
Requires-Dist: slack-sdk<4.0,>=3.36.0
Requires-Dist: sqlalchemy<3.0,>=2.0.0
Requires-Dist: toml<1.0,>=0.10.2
